emonpi_sensors/__init__.py
emonpi_sensors/exceptions.py
emonpi_sensors-0.1.1.dist-info/DESCRIPTION.rst
emonpi_sensors-0.1.1.dist-info/METADATA
emonpi_sensors-0.1.1.dist-info/RECORD
emonpi_sensors-0.1.1.dist-info/WHEEL
emonpi_sensors-0.1.1.dist-info/metadata.json
emonpi_sensors-0.1.1.dist-info/top_level.txt
